softsensor/__init__.py
softsensor/armax.py
softsensor/arx.py
softsensor/autoreg_models.py
softsensor/calibration.py
softsensor/data_gen.py
softsensor/data_prep.py
softsensor/datasets.py
softsensor/ensemble_wrappers.py
softsensor/eval_tools.py
softsensor/frequency_methods.py
softsensor/homoscedastic_model.py
softsensor/hyperparameter_optimization.py
softsensor/layers.py
softsensor/linear_methods.py
softsensor/losses.py
softsensor/meas_handling.py
softsensor/metrics.py
softsensor/model.py
softsensor/recurrent_models.py
softsensor/stab_scheduler.py
softsensor/temporal_fusion_transformer.py
softsensor/train_model.py
softsensor/visualization.py
softsensor-0.1.0rc1.dist-info/licenses/LICENSE
softsensor-0.1.0rc1.dist-info/licenses/NOTICE
softsensor-0.1.0rc1.dist-info/METADATA
softsensor-0.1.0rc1.dist-info/WHEEL
softsensor-0.1.0rc1.dist-info/top_level.txt
softsensor-0.1.0rc1.dist-info/RECORD
