Metadata-Version: 2.4
Name: softsensor
Version: 0.1.0rc1
Summary: A general toolbox for the development of Vibrational Soft-Sensors
Author-email: Westmeier Tobias <tobias.westmeier@de.bosch.com>, Daniel Kreuter <danielchristopher.kreuter@de.bosch.com>
License-Expression: Apache-2.0
Project-URL: repository, https://github.com/boschresearch/vibration-soft-sensor
Project-URL: homepage, https://github.boschdevcloud.com/bios-MSOonGitHub/vibration-soft-sensor
Requires-Python: >=3.12
License-File: LICENSE
License-File: NOTICE
Requires-Dist: darts>=0.35.0
Requires-Dist: hyperopt>=0.2.7
Requires-Dist: matplotlib>=3.10.3
Requires-Dist: numpy>=2.2.6
Requires-Dist: pandas>=2.2.3
Requires-Dist: pylife>=2.1.3
Requires-Dist: scikit-learn>=1.6.1
Requires-Dist: scipy>=1.15.3
Requires-Dist: statsmodels>=0.14.4
Requires-Dist: torch>=2.7.0
Requires-Dist: torchinfo>=1.8.0
Dynamic: license-file
